examples/__init__.py
examples/oauth2.py
examples/oauth2_async.py
examples/save_user_creds.py
examples/spt_keys_template.py
pyfy/__init__.py
pyfy/__version__.py
pyfy/async_client.py
pyfy/base_client.py
pyfy/creds.py
pyfy/excs.py
pyfy/sync_client.py
pyfy/utils.py
pyfy/wrappers.py
tests/__init__.py
tests/conftest.py
tests/run_tests.py
tests/test_integration/__init__.py
tests/test_integration/conftest.py
tests/test_integration/test_async/__init__.py
tests/test_integration/test_async/conftest.py
tests/test_integration/test_async/test_album.py
tests/test_integration/test_async/test_artist.py
tests/test_integration/test_async/test_client_auth.py
tests/test_integration/test_async/test_explore_and_personalization.py
tests/test_integration/test_async/test_gather.py
tests/test_integration/test_async/test_others.py
tests/test_integration/test_async/test_playback.py
tests/test_integration/test_async/test_playlist.py
tests/test_integration/test_async/test_profile.py
tests/test_integration/test_async/test_track.py
tests/test_integration/test_async/test_user.py
tests/test_integration/test_async/test_user_auth.py
tests/test_integration/test_sync/__init__.py
tests/test_integration/test_sync/conftest.py
tests/test_integration/test_sync/test_album.py
tests/test_integration/test_sync/test_artist.py
tests/test_integration/test_sync/test_client_auth.py
tests/test_integration/test_sync/test_explore_and_personlization.py
tests/test_integration/test_sync/test_others.py
tests/test_integration/test_sync/test_playback.py
tests/test_integration/test_sync/test_playlist.py
tests/test_integration/test_sync/test_profile.py
tests/test_integration/test_sync/test_track.py
tests/test_integration/test_sync/test_user.py
tests/test_integration/test_sync/test_user_auth.py
tests/test_units/__init__.py
tests/test_units/test.excs.py
tests/test_units/test_async.py
tests/test_units/test_client.py
tests/test_units/test_creds.py
tests/test_units/test_session.py
tests/test_units/test_utils.py
pyfy-2.2.0.dist-info/LICENSE
pyfy-2.2.0.dist-info/METADATA
pyfy-2.2.0.dist-info/WHEEL
pyfy-2.2.0.dist-info/top_level.txt
pyfy-2.2.0.dist-info/RECORD
