Metadata-Version: 2.1
Name: pyfy
Version: 2.2.0
Summary: Sync/Async API wrapper for Spotify's web API
Home-page: https://github.com/omarryhan/pyfy
Author: Omar Ryhan
Author-email: omarryhan@gmail.com
License: MIT
Platform: UNKNOWN
Classifier: Programming Language :: Python :: 3
Classifier: Operating System :: OS Independent
License-File: LICENSE
Requires-Dist: requests
Requires-Dist: requests[socks]
Requires-Dist: cachecontrol
Requires-Dist: aiohttp
Requires-Dist: backoff
